[
  {
    "model_name":"electra-small-discriminator",
    "parameters":"14M",
    "quantization_status":"baseline",
    "benchmark_suite":"Security",
    "benchmark_name":"ctibench",
    "task_subset":"cti-rcm",
    "peak_vram_gpu_mb":null,
    "peak_ram_system_mb":null,
    "load_time_seconds":4.3920989037,
    "inference_speed_tok_per_sec":null,
    "inference_speed_samples_per_sec":null,
    "avg_inference_time_per_sample_ms":null,
    "hardware":"NVIDIA A40",
    "evaluation_script":"evaluate_cli.py",
    "timestamp":"2025-04-22T21:25:23.000",
    "raw_json_path":"results\/bare\/48\/ctibench_cti-rcm__20250422-212523_metrics.json",
    "score_metric":null,
    "score_value":null,
    "model_size_disk_gb":null
  },
  {
    "model_name":"electra-small-discriminator",
    "parameters":"14M",
    "quantization_status":"baseline",
    "benchmark_suite":"Security",
    "benchmark_name":"ctibench",
    "task_subset":"cti-vsp",
    "peak_vram_gpu_mb":null,
    "peak_ram_system_mb":null,
    "load_time_seconds":4.4322915077,
    "inference_speed_tok_per_sec":null,
    "inference_speed_samples_per_sec":null,
    "avg_inference_time_per_sample_ms":null,
    "hardware":"NVIDIA A40",
    "evaluation_script":"evaluate_cli.py",
    "timestamp":"2025-04-22T21:24:50.000",
    "raw_json_path":"results\/bare\/48\/ctibench_cti-vsp__20250422-212450_metrics.json",
    "score_metric":null,
    "score_value":null,
    "model_size_disk_gb":null
  },
  {
    "model_name":"electra-small-discriminator",
    "parameters":"14M",
    "quantization_status":"baseline",
    "benchmark_suite":"Security",
    "benchmark_name":"ctibench",
    "task_subset":"cti-mcq",
    "peak_vram_gpu_mb":null,
    "peak_ram_system_mb":null,
    "load_time_seconds":4.7064216137,
    "inference_speed_tok_per_sec":null,
    "inference_speed_samples_per_sec":null,
    "avg_inference_time_per_sample_ms":null,
    "hardware":"NVIDIA A40",
    "evaluation_script":"evaluate_cli.py",
    "timestamp":"2025-04-22T21:24:17.000",
    "raw_json_path":"results\/bare\/48\/ctibench_cti-mcq__20250422-212417_metrics.json",
    "score_metric":null,
    "score_value":null,
    "model_size_disk_gb":null
  },
  {
    "model_name":"electra-small-discriminator",
    "parameters":"14M",
    "quantization_status":"baseline",
    "benchmark_suite":"Security",
    "benchmark_name":"sevenllm_bench",
    "task_subset":null,
    "peak_vram_gpu_mb":null,
    "peak_ram_system_mb":null,
    "load_time_seconds":4.6691555977,
    "inference_speed_tok_per_sec":null,
    "inference_speed_samples_per_sec":null,
    "avg_inference_time_per_sample_ms":null,
    "hardware":"NVIDIA A40",
    "evaluation_script":"evaluate_cli.py",
    "timestamp":"2025-04-22T21:23:44.000",
    "raw_json_path":"results\/bare\/48\/sevenllm_bench__20250422-212344_metrics.json",
    "score_metric":null,
    "score_value":null,
    "model_size_disk_gb":null
  },
  {
    "model_name":"electra-small-discriminator",
    "parameters":"14M",
    "quantization_status":"baseline",
    "benchmark_suite":"Security",
    "benchmark_name":"cyberseceval3_mitre",
    "task_subset":null,
    "peak_vram_gpu_mb":null,
    "peak_ram_system_mb":null,
    "load_time_seconds":5.2579629421,
    "inference_speed_tok_per_sec":null,
    "inference_speed_samples_per_sec":null,
    "avg_inference_time_per_sample_ms":null,
    "hardware":"NVIDIA A40",
    "evaluation_script":"evaluate_cli.py",
    "timestamp":"2025-04-22T21:23:13.000",
    "raw_json_path":"results\/bare\/48\/cyberseceval3_mitre__20250422-212313_metrics.json",
    "score_metric":null,
    "score_value":null,
    "model_size_disk_gb":null
  },
  {
    "model_name":"Mistral-7B-Instruct-v0.3",
    "parameters":"7B",
    "quantization_status":"baseline",
    "benchmark_suite":"Security",
    "benchmark_name":"ctibench",
    "task_subset":"cti-rcm",
    "peak_vram_gpu_mb":27976.6459960938,
    "peak_ram_system_mb":1857.2265625,
    "load_time_seconds":74.2141027451,
    "inference_speed_tok_per_sec":18.1234896862,
    "inference_speed_samples_per_sec":0.0937535031,
    "avg_inference_time_per_sample_ms":10666.2681055069,
    "hardware":"NVIDIA A40",
    "evaluation_script":"evaluate_cli.py",
    "timestamp":"2025-04-22T21:03:28.000",
    "raw_json_path":"results\/bare\/48\/ctibench_cti-rcm__20250422-210328_metrics.json",
    "score_metric":null,
    "score_value":null,
    "model_size_disk_gb":null
  },
  {
    "model_name":"Mistral-7B-Instruct-v0.3",
    "parameters":"7B",
    "quantization_status":"baseline",
    "benchmark_suite":"Security",
    "benchmark_name":"ctibench",
    "task_subset":"cti-vsp",
    "peak_vram_gpu_mb":28113.490234375,
    "peak_ram_system_mb":1867.671875,
    "load_time_seconds":25.4998595715,
    "inference_speed_tok_per_sec":17.1737047913,
    "inference_speed_samples_per_sec":0.0436512335,
    "avg_inference_time_per_sample_ms":22908.8600730896,
    "hardware":"NVIDIA A40",
    "evaluation_script":"evaluate_cli.py",
    "timestamp":"2025-04-22T20:23:52.000",
    "raw_json_path":"results\/bare\/48\/ctibench_cti-vsp__20250422-202352_metrics.json",
    "score_metric":null,
    "score_value":null,
    "model_size_disk_gb":null
  },
  {
    "model_name":"Mistral-7B-Instruct-v0.3",
    "parameters":"7B",
    "quantization_status":"baseline",
    "benchmark_suite":"Security",
    "benchmark_name":"ctibench",
    "task_subset":"cti-mcq",
    "peak_vram_gpu_mb":27755.52734375,
    "peak_ram_system_mb":1869.5390625,
    "load_time_seconds":75.1007239819,
    "inference_speed_tok_per_sec":12.5345150939,
    "inference_speed_samples_per_sec":1.4115444926,
    "avg_inference_time_per_sample_ms":708.44383955,
    "hardware":"NVIDIA A40",
    "evaluation_script":"evaluate_cli.py",
    "timestamp":"2025-04-22T20:20:49.000",
    "raw_json_path":"results\/bare\/48\/ctibench_cti-mcq__20250422-202049_metrics.json",
    "score_metric":null,
    "score_value":null,
    "model_size_disk_gb":null
  },
  {
    "model_name":"Mistral-7B-Instruct-v0.3",
    "parameters":"7B",
    "quantization_status":"baseline",
    "benchmark_suite":"Security",
    "benchmark_name":"sevenllm_bench",
    "task_subset":null,
    "peak_vram_gpu_mb":28117.0288085938,
    "peak_ram_system_mb":1851.015625,
    "load_time_seconds":68.787974596,
    "inference_speed_tok_per_sec":17.2272260975,
    "inference_speed_samples_per_sec":0.0675736491,
    "avg_inference_time_per_sample_ms":14798.6680245399,
    "hardware":"NVIDIA A40",
    "evaluation_script":"evaluate_cli.py",
    "timestamp":"2025-04-22T19:54:13.000",
    "raw_json_path":"results\/bare\/48\/sevenllm_bench__20250422-195413_metrics.json",
    "score_metric":null,
    "score_value":null,
    "model_size_disk_gb":null
  },
  {
    "model_name":"Mistral-7B-Instruct-v0.3",
    "parameters":"7B",
    "quantization_status":"baseline",
    "benchmark_suite":"Security",
    "benchmark_name":"cyberseceval3_mitre",
    "task_subset":null,
    "peak_vram_gpu_mb":27941.5234375,
    "peak_ram_system_mb":1858.72265625,
    "load_time_seconds":73.3036878109,
    "inference_speed_tok_per_sec":17.5179994861,
    "inference_speed_samples_per_sec":0.0343515133,
    "avg_inference_time_per_sample_ms":29110.7990594558,
    "hardware":"NVIDIA A40",
    "evaluation_script":"evaluate_cli.py",
    "timestamp":"2025-04-22T19:12:51.000",
    "raw_json_path":"results\/bare\/48\/cyberseceval3_mitre__20250422-191251_metrics.json",
    "score_metric":null,
    "score_value":null,
    "model_size_disk_gb":null
  },
  {
    "model_name":"Phi-3-mini-4k-instruct",
    "parameters":"Unknown",
    "quantization_status":"baseline",
    "benchmark_suite":"Security",
    "benchmark_name":"ctibench",
    "task_subset":"cti-rcm",
    "peak_vram_gpu_mb":15760.5283203125,
    "peak_ram_system_mb":1312.08203125,
    "load_time_seconds":43.3360097408,
    "inference_speed_tok_per_sec":32.061822221,
    "inference_speed_samples_per_sec":0.2521971385,
    "avg_inference_time_per_sample_ms":3965.1520466805,
    "hardware":"NVIDIA A40",
    "evaluation_script":"evaluate_cli.py",
    "timestamp":"2025-04-22T19:04:48.000",
    "raw_json_path":"results\/bare\/48\/ctibench_cti-rcm__20250422-190448_metrics.json",
    "score_metric":null,
    "score_value":null,
    "model_size_disk_gb":null
  },
  {
    "model_name":"Phi-3-mini-4k-instruct",
    "parameters":"Unknown",
    "quantization_status":"baseline",
    "benchmark_suite":"Security",
    "benchmark_name":"ctibench",
    "task_subset":"cti-vsp",
    "peak_vram_gpu_mb":16347.7241210938,
    "peak_ram_system_mb":1337.7109375,
    "load_time_seconds":15.276558876,
    "inference_speed_tok_per_sec":30.6050195193,
    "inference_speed_samples_per_sec":0.0799525053,
    "avg_inference_time_per_sample_ms":12507.4254488945,
    "hardware":"NVIDIA A40",
    "evaluation_script":"evaluate_cli.py",
    "timestamp":"2025-04-22T18:42:59.000",
    "raw_json_path":"results\/bare\/48\/ctibench_cti-vsp__20250422-184259_metrics.json",
    "score_metric":null,
    "score_value":null,
    "model_size_disk_gb":null
  },
  {
    "model_name":"Phi-3-mini-4k-instruct",
    "parameters":"Unknown",
    "quantization_status":"baseline",
    "benchmark_suite":"Security",
    "benchmark_name":"ctibench",
    "task_subset":"cti-mcq",
    "peak_vram_gpu_mb":14943.6547851562,
    "peak_ram_system_mb":1305.0625,
    "load_time_seconds":44.4016029835,
    "inference_speed_tok_per_sec":11.5122731315,
    "inference_speed_samples_per_sec":5.7561365657,
    "avg_inference_time_per_sample_ms":173.7276363373,
    "hardware":"NVIDIA A40",
    "evaluation_script":"evaluate_cli.py",
    "timestamp":"2025-04-22T18:41:25.000",
    "raw_json_path":"results\/bare\/48\/ctibench_cti-mcq__20250422-184125_metrics.json",
    "score_metric":null,
    "score_value":null,
    "model_size_disk_gb":null
  },
  {
    "model_name":"Phi-3-mini-4k-instruct",
    "parameters":"Unknown",
    "quantization_status":"baseline",
    "benchmark_suite":"Security",
    "benchmark_name":"sevenllm_bench",
    "task_subset":null,
    "peak_vram_gpu_mb":16362.3857421875,
    "peak_ram_system_mb":1307.94921875,
    "load_time_seconds":64.6725127697,
    "inference_speed_tok_per_sec":30.7525421526,
    "inference_speed_samples_per_sec":0.1043803617,
    "avg_inference_time_per_sample_ms":9580.3461885452,
    "hardware":"NVIDIA A40",
    "evaluation_script":"evaluate_cli.py",
    "timestamp":"2025-04-22T18:23:36.000",
    "raw_json_path":"results\/bare\/48\/sevenllm_bench__20250422-182336_metrics.json",
    "score_metric":null,
    "score_value":null,
    "model_size_disk_gb":null
  },
  {
    "model_name":"Phi-3-mini-4k-instruct",
    "parameters":"Unknown",
    "quantization_status":"baseline",
    "benchmark_suite":"Security",
    "benchmark_name":"cyberseceval3_mitre",
    "task_subset":null,
    "peak_vram_gpu_mb":15443.9482421875,
    "peak_ram_system_mb":1305.140625,
    "load_time_seconds":44.8786327839,
    "inference_speed_tok_per_sec":31.2756050765,
    "inference_speed_samples_per_sec":0.0765840567,
    "avg_inference_time_per_sample_ms":13057.5480490555,
    "hardware":"NVIDIA A40",
    "evaluation_script":"evaluate_cli.py",
    "timestamp":"2025-04-22T18:03:14.000",
    "raw_json_path":"results\/bare\/48\/cyberseceval3_mitre__20250422-180314_metrics.json",
    "score_metric":null,
    "score_value":null,
    "model_size_disk_gb":null
  },
  {
    "model_name":"TinyLlama-1.1B-Chat-v1.0",
    "parameters":"1.1B",
    "quantization_status":"baseline",
    "benchmark_suite":"Security",
    "benchmark_name":"ctibench",
    "task_subset":"cti-rcm",
    "peak_vram_gpu_mb":4301.6430664062,
    "peak_ram_system_mb":1727.91015625,
    "load_time_seconds":8.4939668179,
    "inference_speed_tok_per_sec":64.2126295763,
    "inference_speed_samples_per_sec":0.209858911,
    "avg_inference_time_per_sample_ms":4765.1062107086,
    "hardware":"NVIDIA A40",
    "evaluation_script":"evaluate_cli.py",
    "timestamp":"2025-04-22T17:54:38.000",
    "raw_json_path":"results\/bare\/48\/ctibench_cti-rcm__20250422-175438_metrics.json",
    "score_metric":null,
    "score_value":null,
    "model_size_disk_gb":null
  },
  {
    "model_name":"TinyLlama-1.1B-Chat-v1.0",
    "parameters":"1.1B",
    "quantization_status":"baseline",
    "benchmark_suite":"Security",
    "benchmark_name":"ctibench",
    "task_subset":"cti-vsp",
    "peak_vram_gpu_mb":4345.7431640625,
    "peak_ram_system_mb":1735.8671875,
    "load_time_seconds":8.5376393795,
    "inference_speed_tok_per_sec":68.2900273719,
    "inference_speed_samples_per_sec":0.2043143471,
    "avg_inference_time_per_sample_ms":4894.4188904762,
    "hardware":"NVIDIA A40",
    "evaluation_script":"evaluate_cli.py",
    "timestamp":"2025-04-22T17:45:51.000",
    "raw_json_path":"results\/bare\/48\/ctibench_cti-vsp__20250422-174551_metrics.json",
    "score_metric":null,
    "score_value":null,
    "model_size_disk_gb":null
  },
  {
    "model_name":"TinyLlama-1.1B-Chat-v1.0",
    "parameters":"1.1B",
    "quantization_status":"baseline",
    "benchmark_suite":"Security",
    "benchmark_name":"ctibench",
    "task_subset":"cti-mcq",
    "peak_vram_gpu_mb":4235.5239257812,
    "peak_ram_system_mb":1706.55859375,
    "load_time_seconds":27.6254484653,
    "inference_speed_tok_per_sec":59.6831179036,
    "inference_speed_samples_per_sec":1.5949523758,
    "avg_inference_time_per_sample_ms":626.9779682159,
    "hardware":"NVIDIA A40",
    "evaluation_script":"evaluate_cli.py",
    "timestamp":"2025-04-22T17:43:49.000",
    "raw_json_path":"results\/bare\/48\/ctibench_cti-mcq__20250422-174349_metrics.json",
    "score_metric":null,
    "score_value":null,
    "model_size_disk_gb":null
  },
  {
    "model_name":"TinyLlama-1.1B-Chat-v1.0",
    "parameters":"1.1B",
    "quantization_status":"baseline",
    "benchmark_suite":"Security",
    "benchmark_name":"sevenllm_bench",
    "task_subset":null,
    "peak_vram_gpu_mb":4345.2309570312,
    "peak_ram_system_mb":1707.9453125,
    "load_time_seconds":30.0715792179,
    "inference_speed_tok_per_sec":68.6237246473,
    "inference_speed_samples_per_sec":0.1683893815,
    "avg_inference_time_per_sample_ms":5938.6167407036,
    "hardware":"NVIDIA A40",
    "evaluation_script":"evaluate_cli.py",
    "timestamp":"2025-04-22T17:32:36.000",
    "raw_json_path":"results\/bare\/48\/sevenllm_bench__20250422-173236_metrics.json",
    "score_metric":null,
    "score_value":null,
    "model_size_disk_gb":null
  },
  {
    "model_name":"TinyLlama-1.1B-Chat-v1.0",
    "parameters":"1.1B",
    "quantization_status":"baseline",
    "benchmark_suite":"Security",
    "benchmark_name":"cyberseceval3_mitre",
    "task_subset":null,
    "peak_vram_gpu_mb":4275.9067382812,
    "peak_ram_system_mb":1654.4375,
    "load_time_seconds":28.046671629,
    "inference_speed_tok_per_sec":67.581262958,
    "inference_speed_samples_per_sec":0.1327597385,
    "avg_inference_time_per_sample_ms":7532.404107812,
    "hardware":"NVIDIA A40",
    "evaluation_script":"evaluate_cli.py",
    "timestamp":"2025-04-22T17:21:06.000",
    "raw_json_path":"results\/bare\/48\/cyberseceval3_mitre__20250422-172106_metrics.json",
    "score_metric":null,
    "score_value":null,
    "model_size_disk_gb":null
  }
]